{
  "https://phoneclinicpro.com/": {
    "online": true,
    "verificado_em": "22/07/2026 06:17 UTC"
  },
  "https://voosriopan.com/": {
    "online": true,
    "verificado_em": "22/07/2026 06:17 UTC"
  },
  "https://easyflighttour.com.br/": {
    "online": true,
    "verificado_em": "22/07/2026 06:17 UTC"
  },
  "https://intestinon.com.br/": {
    "online": true,
    "verificado_em": "22/07/2026 06:17 UTC"
  },
  "https://larissairala.com.br/": {
    "online": true,
    "verificado_em": "22/07/2026 06:17 UTC"
  }
}