{
  "https://phoneclinicpro.com/": {
    "online": true,
    "verificado_em": "21/07/2026 23:09 UTC"
  },
  "https://voosriopan.com/": {
    "online": true,
    "verificado_em": "21/07/2026 23:09 UTC"
  },
  "https://easyflighttour.com.br/": {
    "online": true,
    "verificado_em": "21/07/2026 23:09 UTC"
  },
  "https://intestinon.com.br/": {
    "online": true,
    "verificado_em": "21/07/2026 23:09 UTC"
  },
  "https://larissairala.com.br/": {
    "online": true,
    "verificado_em": "21/07/2026 23:09 UTC"
  }
}